fast_pl_py-1.3.0.dist-info/METADATA
fast_pl_py-1.3.0.dist-info/WHEEL
rpls_py/__init__.py
rpls_py/rpls_py.cpython-312-x86_64-linux-gnu.so
fast_pl_py-1.3.0.dist-info/RECORD
